code_stats/__init__.py
code_stats/cli.py
code_stats/definitions.py
code_stats/bin/__init__.py
code_stats/bin/data_reader.py
code_stats/bin/logger.py
code_stats/bin/statistics.py
code_stats/data/codestats_sample.png
code_stats/data/default_ext_list.yml
code_stats/data/default_languages.json
code_stats/tests/__init__.py
code_stats/tests/test_statistics.py
code_stats/tests/test_utils.py
code_stats/tests/testing_data/test_file.json
code_stats/tests/testing_data/test_file.py
code_stats/utils/__init__.py
code_stats/utils/conversion_utils.py
code_stats/utils/files_and_folders_utils.py
code_stats/utils/print_utils.py
code_stats/utils/validation_utils.py
code_stats-0.1.1.dist-info/LICENSE.txt
code_stats-0.1.1.dist-info/METADATA
code_stats-0.1.1.dist-info/WHEEL
code_stats-0.1.1.dist-info/entry_points.txt
code_stats-0.1.1.dist-info/top_level.txt
code_stats-0.1.1.dist-info/RECORD
