Metadata-Version: 2.1
Name: code-stats
Version: 0.1.1
Summary: A command line tool to generate code statistics for a given directory.
Home-page: https://github.com/abhinavshaw1993/code-stats
Author: Abhinav Shaw
Author-email: abhinav.shaw1993@gmail.com
License: UNKNOWN
Keywords: Code statistics,lines of code,loc
Platform: UNKNOWN
Classifier: Programming Language :: Python :: 3
Classifier: Operating System :: POSIX :: Linux
Requires-Dist: click
Requires-Dist: pathlib
